reyweb/__init__.py
reyweb/rall.py
reyweb/rbase.py
reyweb/rapi/__init__.py
reyweb/rapi/rali.py
reyweb/rapi/rbaidu.py
reyweb/rapi/rdb.py
reyweb-1.1.34.dist-info/METADATA
reyweb-1.1.34.dist-info/WHEEL
reyweb-1.1.34.dist-info/licenses/LICENSE
reyweb-1.1.34.dist-info/RECORD
