Metadata-Version: 2.4
Name: reyweb
Version: 1.1.34
Summary: Web method set.
Project-URL: homepage, https://github.com/reyxbo/reyweb/
Author-email: Rey <reyxbo@163.com>
License: Copyright 2025 ReyXBo
License-File: LICENSE
Keywords: api,rey,reyxbo,web
Requires-Python: >=3.12
Requires-Dist: reykit
